{
  "car": [
    {
      "carName": "Volvo",
      "type": "GCBA",
      "marking": "5/32",
      "dateEntry": "2024-03-17T23:00:00.000Z",
      "destiny": 2,
      "operationalNumber": "421-22",
      "employee": {
        "name": "Artur",
        "surname": "Izdebski"
      },
      "id": 2,
      "link": "http://localhost:4200/assets/images/GCBA_VOLVO.jpg"
    },
    {
      "carName": "Tatra",
      "type": "GCBA",
      "marking": "5/32",
      "dateEntry": "2024-03-17T23:00:00.000Z",
      "destiny": 2,
      "operationalNumber": "421-22",
      "employee": {
        "name": "John",
        "surname": "Kowalski"
      },
      "id": 3,
      "link": "http://localhost:4200/assets/images/GBA_TATRA.jpg"
    },
    {
      "carName": "Man",
      "type": "GCBA",
      "marking": "5/32",
      "dateEntry": "2024-03-17T23:00:00.000Z",
      "destiny": 2,
      "operationalNumber": "421-22",
      "employee": {
        "name": "John",
        "surname": "Kowalski"
      },
      "id": 4,
      "link": "http://localhost:4200/assets/images/GBA_MAN.jpg"
    }
  ],
  "elements": [
    { "section": "KABINA", "position": null, "name": "", "count": null, "comments": "" },
    { "position": 1, "name": "Radio samochodowe Volvo", "count": 1, "comments": "sprawne" },
    { "position": 2, "name": "Model radiowy pojazdu", "count": 1, "comments": "gotowy do użycia" },
  
    { "section": "SKRYTKA NR 1", "position": null, "name": "", "count": null, "comments": "" },
    { "position": 3, "name": "Butle powietrze do poduszek", "count": 1, "comments": "" },
    { "position": 4, "name": "Reduktor do butli", "count": 1, "comments": "" }
 
  ]
}
